
{
   "files": [    



{
         "name": "FREE-AIS-MOBILE-TH",
         "url": "ZfTFvMIfGqOfkyJUBHatFXyW7320NCvPw9fAAIoZGH2jnp552vTgOR4Qt6lD0DMi/CVivscAyuQwgsfudWb/E6g18Rilbn5q"
      }
,
{
         "name": "FREE-DTAC-MOBILE-TH",
         "url": "8RGAcu+vLBgvIW/m8nlgBrsnF11LUDDMCBSBmwCvlmaa9hI0kzYKpCdyAX48uoMT49ttNNlmRt6yqYO22zX9UJmSomDcUp/s"
      }
,
{
         "name": "FREE-TRUE-MOBILE-TH",
         "url": "aYtc5o5or01kGG4xF+N+cdnVPnlcjPY7Yeb3jCSwcJy++FGalOXdm74PSpJVMQ1bvXguSBwJcsNHPKGt2E7RpROIIF78GbmX"
      }


   ],
"message":"
ЁЯЫар╣Вр╕Ыр╕гр╕Фр╕нр╣Ир╕▓р╕Щр╕кр╕▒р╕Бр╕Щр╕┤р╕Фр╕Щр╕░р╕Др╕гр╕▒р╕Ъ
[р╕кр╕▓р╕бр╕▓р╕гр╕Цр╣Ар╕ер╕╖р╣Ир╕нр╕Щр╕Вр╕╢р╣Йр╕Щр╕ер╕Зр╣Др╕Фр╣Йр╕Др╕гр╕▒р╕Ъ]
ЁЯУБр╣Ар╕Лр╕┤р╕гр╣Мр╕Яр╣Ар╕зр╕нр╕гр╣М FREE-TRUE-MOBILE-TH [р╕Яр╕гр╕╡]


[р╣Гр╕Щр╣Др╕Ыр╕Бр╕гр╕нр╕Бр╣Гр╕кр╣Ир╕Хр╕▓р╕бр╕Кр╣Ир╕нр╕Зр╣Др╕Фр╣Йр╣Ар╕ер╕вр╕Щр╕░р╕Др╕гр╕▒р╕Ъ]
#р╣Бр╕Щр╕░р╕Щр╕│р╣Гр╕лр╣Йр╣Бр╕Др╣Кр╕Ыр╕лр╕Щр╣Йр╕▓р╕Ир╕нр╣Др╕зр╣Йр╕Щр╣Йр╕▓
ЁЯФПр╕Кр╕╖р╣Ир╕нр╕Ьр╕╣р╣Йр╣Гр╕Кр╣Й : FREE30DAY
ЁЯФПр╕гр╕лр╕▒р╕кр╕Ьр╣Ир╕▓р╕Щ : 0001
тЭМя╕Пр╕лр╕бр╕Фр╕зр╕▒р╕Щр╕Чр╕╡р╣И 28 / 12 /2033


ЁЯл░ЁЯП╗ЁЯдНр╣Вр╕Ыр╕гр╣Ар╕кр╕гр╕┤р╕бр╕Чр╕╡р╣Ир╕Хр╣Йр╕нр╕Зр╣Гр╕Кр╣Й
#р╣Бр╕Щр╕░р╕Щр╕│р╣Гр╕лр╣Йр╣Бр╕Др╣Кр╕Ыр╕лр╕Щр╣Йр╕▓р╕Ир╕нр╣Др╕зр╣Йр╕Щр╣Йр╕▓

ЁЯНгA I S #р╣Бр╕Щр╕░р╕Щр╕│р╣Гр╕лр╣Йр╣Бр╕Др╣Кр╕Ыр╕лр╕Щр╣Йр╕▓р╕Ир╕нр╣Др╕зр╣Йр╕Щр╣Йр╕▓

ЁЯТ╝р╕кр╕бр╕▒р╕Др╕гр╣Вр╕Ыр╕гр╣Ар╕кр╕гр╕┤р╕б 64Kbps+Ais р╣Ар╕Юр╕вр╣М
р╕Цр╣Йр╕▓р╕кр╕бр╕▒р╕Др╕гр╣Вр╕Ыр╕гр╕Щр╕╡р╣Йр╣Бр╕ер╣Йр╕зр╣Гр╕лр╣Йр╣Ар╕ер╕╖р╕нр╕Бр╣Гр╕Кр╣Йр╣Др╕Яр╕ер╣М "Ais+64Kb-р╣Ар╕Юр╕вр╣М"
р╕Др╣Ир╕▓р╕кр╕бр╕▒р╕Др╕гр╣Вр╕Ыр╕гр╣Вр╕бр╕Кр╕▒р╣Ир╕Щ 30 р╕Ър╕▓р╕Ч / 30 р╕зр╕▒р╕Щ 
(р╕гр╕зр╕бр╕ар╕▓р╕йр╕╡ 31.03 р╕Ър╕▓р╕Ч)

ЁЯЪер╕зр╕┤р╕Шр╕╡р╕Бр╕Фр╕кр╕бр╕▒р╕Др╕г *777*7067# ЁЯУЮ

р╣Гр╕Кр╣Йр╕Др╕╣р╣Ир╕Бр╕▒р╕Ър╣Вр╕Ыр╕г Ais Play
р╕Др╣Ир╕▓р╕кр╕бр╕▒р╕Др╕гр╣Вр╕Ыр╕гр╣Вр╕бр╕Кр╕▒р╣Ир╕Щ 9 р╕Ър╕▓р╕Ч / 1 р╕зр╕▒р╕Щ
р╕зр╕┤р╕Шр╕╡р╕Бр╕Фр╕кр╕бр╕▒р╕Др╕г *777*7310*123456# ЁЯУЮ
р╕Др╣Ир╕▓р╕кр╕бр╕▒р╕Др╕гр╣Вр╕Ыр╕гр╣Вр╕бр╕Кр╕▒р╣Ир╕Щ 19 р╕Ър╕▓р╕Ч / 7 р╕зр╕▒р╕Щ
р╕зр╕┤р╕Шр╕╡р╕Бр╕Фр╕кр╕бр╕▒р╕Др╕г *777*7311*123456# ЁЯУЮ
р╕Др╣Ир╕▓р╕кр╕бр╕▒р╕Др╕гр╣Вр╕Ыр╕гр╣Вр╕бр╕Кр╕▒р╣Ир╕Щ 59 р╕Ър╕▓р╕Ч / 30 р╕зр╕▒р╕Щ
р╕зр╕┤р╕Шр╕╡р╕Бр╕Фр╕кр╕бр╕▒р╕Др╕г *777*885*123456# ЁЯУЮ

ЁЯНгD T A C #р╣Бр╕Щр╕░р╕Щр╕│р╣Гр╕лр╣Йр╣Бр╕Др╣Кр╕Ыр╕лр╕Щр╣Йр╕▓р╕Ир╕нр╣Др╕зр╣Йр╕Щр╣Йр╕▓

ЁЯМИр╕кр╕бр╕▒р╕Др╕гр╣Вр╕Ыр╕гр╣Ар╕кр╕гр╕┤р╕б р╣Бр╕ор╕Ыр╕Ыр╕╡р╣Йр╣Др╕ер╕Щр╣М

р╕Др╣Ир╕▓р╕кр╕бр╕▒р╕Др╕гр╣Вр╕Ыр╕гр╣Вр╕бр╕Кр╕▒р╣Ир╕Щ 49 р╕Ър╕▓р╕Ч / 30 р╕зр╕▒р╕Щ (р╕гр╕зр╕бр╕ар╕▓р╕йр╕╡ 52.43 р╕Ър╕▓р╕Ч)

тШДя╕Пр╕зр╕┤р╕Шр╕╡р╕Бр╕Фр╕кр╕бр╕▒р╕Др╕г *104*777# ЁЯУЮ
р╣Ар╕Йр╕Юр╕▓р╕░р╣Вр╕Ыр╕гр╕Щр╕╡р╣Йр╕Хр╣Йр╕нр╕Зр╣Гр╕Кр╣Йр╕Др╕╣р╣Ир╕Бр╕▒р╕Ър╕нр╕┤р╕Щр╣Ар╕Чр╕нр╕гр╣Мр╣Ар╕Щр╣Зр╕Хр╕Бр╕▒р╕Щр╣Ар╕Щр╣Зр╕Хр╕гр╕▒р╣Ир╕з
р╕Др╣Ир╕▓р╕кр╕бр╕▒р╕Др╕гр╣Вр╕Ыр╕гр╣Вр╕бр╕Кр╕▒р╣Ир╕Щ 20 р╕Ър╕▓р╕Ч / 30 р╕зр╕▒р╕Щ
р╕зр╕┤р╕Шр╕╡р╕Бр╕Фр╕кр╕бр╕▒р╕Др╕г *117*30# ЁЯУЮ

ЁЯНгT R U E #р╣Бр╕Щр╕░р╕Щр╕│р╣Гр╕лр╣Йр╣Бр╕Др╣Кр╕Ыр╕лр╕Щр╣Йр╕▓р╕Ир╕нр╣Др╕зр╣Йр╕Щр╣Йр╕▓

ЁЯеГр╕кр╕бр╕▒р╕Др╕гр╣Вр╕Ыр╕гр╣Вр╕бр╕Кр╕▒р╣Ир╕Щр╣Ар╕кр╕гр╕┤р╕б р╕вр╕╣р╕Чр╕╣р╕Ы

р╕Др╣Ир╕▓р╕кр╕бр╕▒р╕Др╕гр╣Вр╕Ыр╕гр╣Вр╕бр╕Кр╕▒р╣Ир╕Щ 9.63 р╕Ър╕▓р╕Ч / 1 р╕зр╕▒р╕Щ / 500Mb
р╕зр╕┤р╕Шр╕╡р╕Бр╕Фр╕кр╕бр╕▒р╕Др╕г *900*3965# ЁЯУЮ
р╕Др╣Ир╕▓р╕кр╕бр╕▒р╕Др╕гр╣Вр╕Ыр╕гр╣Вр╕бр╕Кр╕▒р╣Ир╕Щ 20.33 р╕Ър╕▓р╕Ч / 7 р╕зр╕▒р╕Щ / 2.5Gb
р╕зр╕┤р╕Шр╕╡р╕Бр╕Фр╕кр╕бр╕▒р╕Др╕г *900*3966# ЁЯУЮ
р╕Др╣Ир╕▓р╕кр╕бр╕▒р╕Др╕гр╣Вр╕Ыр╕гр╣Вр╕бр╕Кр╕▒р╣Ир╕Щ 63.13 р╕Ър╕▓р╕Ч / 30 р╕зр╕▒р╕Щ / 7.5Gb
р╕зр╕┤р╕Шр╕╡р╕Бр╕Фр╕кр╕бр╕▒р╕Др╕г *900*3967# ЁЯУЮ
р╕кр╕бр╕▒р╕Др╕гр╣Бр╕ер╣Йр╕з р╣Ар╕Кр╕╖р╣Ир╕нр╕бр╕Хр╣Ир╕нVPN р╣Ар╕ер╣Ир╕Щр╕нр╕┤р╕Щр╣Ар╕Хр╕нр╕гр╣Мр╣Ар╕Щр╣Зр╕Хр╣Бр╕гр╕Зр╣Др╕бр╣Ир╕Ир╕│р╕Бр╕▒р╕Ф
\n\nUpdate:1",
"title":"New Update File" ,
   "version":16
}
